celery_sprout-0.0.3.dist-info/DESCRIPTION.rst
celery_sprout-0.0.3.dist-info/METADATA
celery_sprout-0.0.3.dist-info/metadata.json
celery_sprout-0.0.3.dist-info/RECORD
celery_sprout-0.0.3.dist-info/top_level.txt
celery_sprout-0.0.3.dist-info/WHEEL
sprout/__init__.py
