Metadata-Version: 2.0
Name: celery-sprout
Version: 0.0.3
Summary: Generate Web UI to run Celery tasks
Home-page: https://github.com/zzzap/celery-sprout
Author: Vladimir Makushkin
Author-email: makushkin.v@gmail.com
License: MIT
Download-URL: https://github.com/zzzap/celery-sprout/tarball/0.0.3
Keywords: celery
Platform: UNKNOWN
Classifier: Development Status :: 3 - Alpha
Classifier: Programming Language :: Python
Classifier: Programming Language :: Python :: 2
Classifier: Programming Language :: Python :: 2.7
Classifier: Programming Language :: Python :: 3
Classifier: Programming Language :: Python :: 3.3
Classifier: Programming Language :: Python :: 3.4
Requires-Dist: celery (>=3.0)
